lcreg/__init__.py
lcreg/image3d.py
lcreg/image_transform.py
lcreg/isq_to_mhd.py
lcreg/lcreg.py
lcreg/lcreg_lib.cpython-39-darwin.so
lcreg/lcreg_util.py
lcreg/masking.py
lcreg/multires_pyramid.py
lcreg/optimisation.py
lcreg/similarity.py
lcreg/view_compressed_images.py
lcreg-1.0.1.dist-info/LICENSE.txt
lcreg-1.0.1.dist-info/METADATA
lcreg-1.0.1.dist-info/WHEEL
lcreg-1.0.1.dist-info/entry_points.txt
lcreg-1.0.1.dist-info/top_level.txt
lcreg-1.0.1.dist-info/RECORD
