Metadata-Version: 2.1
Name: lcreg
Version: 1.0.1
Summary: Efficient 3D rigid and affine image registration
Home-page: https://github.com/p-roesch/lcreg
Author: Peter Rösch
Author-email: lcreg@hs-augsburg.de
License: GPLv3
Project-URL: ResearchGate Project, https://www.researchgate.net/project/Efficient-registration-of-large-3D-images-lcreg
Keywords: 3D image registration
Classifier: Development Status :: 5 - Production/Stable
Classifier: License :: OSI Approved :: GNU General Public License v3 or later (GPLv3+)
Classifier: Operating System :: OS Independent
Classifier: Programming Language :: Python :: 3
Classifier: Environment :: Console
Classifier: Intended Audience :: Science/Research
Classifier: Programming Language :: Cython
Classifier: Programming Language :: Python :: 3 :: Only
Requires-Python: >=3, <4
License-File: LICENSE.txt
Requires-Dist: numpy (>=1.21)
Requires-Dist: scipy (>=1.7)
Requires-Dist: bcolz (>=1.2)
Requires-Dist: psutil (>=5.8)
Requires-Dist: py-cpuinfo (>=8.0)
